src/formatter.py
src/library.py
src/logger.py
src/main.py
src/spreadsheet.py
src/symbol.py
kiskeleton-0.1.1.dist-info/METADATA
kiskeleton-0.1.1.dist-info/WHEEL
kiskeleton-0.1.1.dist-info/entry_points.txt
kiskeleton-0.1.1.dist-info/top_level.txt
kiskeleton-0.1.1.dist-info/RECORD
