Metadata-Version: 2.4
Name: kiskeleton
Version: 0.1.1
Summary: Derive and modify KiCad symbol libraries with spreadsheets
Requires-Python: >=3.13
Requires-Dist: sexpdata>=1.0.2
